lpr_model/__init__.py
lpr_model/configuration_lpr.py
lpr_model/modeling_lpr.py
lpr_model-1.1.1.dist-info/METADATA
lpr_model-1.1.1.dist-info/WHEEL
lpr_model-1.1.1.dist-info/top_level.txt
lpr_model-1.1.1.dist-info/RECORD
