Metadata-Version: 2.4
Name: lpr_model
Version: 1.1.1
Summary: A custom LPR model for lipid-binding Protein prediction
Home-page: https://huggingface.co/Noora68/lpr-0.4B
Author: FeitongDong
Author-email: one@ldu.edu.cn
License: MIT
Classifier: Programming Language :: Python :: 3
Classifier: License :: OSI Approved :: MIT License
Classifier: Operating System :: OS Independent
Requires-Python: >=3.8
Requires-Dist: torch>=2.7.0
Requires-Dist: transformers>=4.32.0
Requires-Dist: esm>=0.5.0
Dynamic: author
Dynamic: author-email
Dynamic: classifier
Dynamic: description
Dynamic: description-content-type
Dynamic: home-page
Dynamic: license
Dynamic: requires-dist
Dynamic: requires-python
Dynamic: summary
